AUTHORS
CHANGELOG
LICENSE
MANIFEST.in
README
README.rst
setup.py
cities_light_py3/__init__.py
cities_light_py3/abstract_models.py
cities_light_py3/admin.py
cities_light_py3/downloader.py
cities_light_py3/exceptions.py
cities_light_py3/forms.py
cities_light_py3/geonames.py
cities_light_py3/loading.py
cities_light_py3/models.py
cities_light_py3/receivers.py
cities_light_py3/settings.py
cities_light_py3/signals.py
cities_light_py3/validators.py
django_cities_light_py3.egg-info/PKG-INFO
django_cities_light_py3.egg-info/SOURCES.txt
django_cities_light_py3.egg-info/dependency_links.txt
django_cities_light_py3.egg-info/not-zip-safe
django_cities_light_py3.egg-info/requires.txt
django_cities_light_py3.egg-info/top_level.txt