Metadata-Version: 1.1
Name: django-cities-light-py3
Version: 3.5.2
Summary: Simple alternative to django-cities
Home-page: https://github.com/nguyencg/django-cities-light
Author: James Pic,Dominick Rivard,Alexey Evseev
Author-email: jamespic@gmail.com, dominick.rivard@gmail.com, myhappydo@gmail.com
License: MIT
Keywords: django cities countries postal codes
Platform: UNKNOWN
Classifier: Development Status :: 5 - Production/Stable
Classifier: Environment :: Web Environment
Classifier: Framework :: Django
Classifier: Intended Audience :: Developers
Classifier: License :: OSI Approved :: MIT License
Classifier: Operating System :: OS Independent
Classifier: Programming Language :: Python
Classifier: Programming Language :: Python :: 2
Classifier: Programming Language :: Python :: 3
Classifier: Topic :: Internet :: WWW/HTTP
Classifier: Topic :: Software Development :: Libraries :: Python Modules
